norske_kommuner/__init__.py
norske_kommuner/kommuner.py
norske_kommuner/models.py
norske_kommuner/resources/1236.csv
norske_kommuner/resources/fylkeskommuner.json
norske_kommuner/resources/openapi.json
norske_kommuner-0.4.0.dist-info/METADATA
norske_kommuner-0.4.0.dist-info/WHEEL
norske_kommuner-0.4.0.dist-info/RECORD
