Metadata-Version: 2.1
Name: norske-kommuner
Version: 0.4.0
Summary: Pydantic models on Norwegian municipalities (Norske kommuner).
Home-page: https://github.com/AndersSteenNilsen/norske-kommuner
Keywords: kommuner,municipalities,norway
Author: Anders Steen
Author-email: asteennilsen@gmail.com
Requires-Python: >=3.7,<4.0
Classifier: Development Status :: 3 - Alpha
Classifier: Programming Language :: Python :: 3
Classifier: Programming Language :: Python :: 3.7
Classifier: Programming Language :: Python :: 3.8
Classifier: Programming Language :: Python :: 3.9
Classifier: Programming Language :: Python :: 3.10
Classifier: Programming Language :: Python :: 3.11
Classifier: Programming Language :: Python :: 3.12
Requires-Dist: attrs (>=23.1.0,<24.0.0)
Requires-Dist: pydantic (>=2.5.1,<3.0.0)
Project-URL: Repository, https://github.com/AndersSteenNilsen/norske-kommuner
